odoo/addons/l10n_es_intrastat_report/README.rst
odoo/addons/l10n_es_intrastat_report/__init__.py
odoo/addons/l10n_es_intrastat_report/__manifest__.py
odoo/addons/l10n_es_intrastat_report/data/NC_20.xlsx
odoo/addons/l10n_es_intrastat_report/data/intrastat_transaction.xml
odoo/addons/l10n_es_intrastat_report/i18n/es.po
odoo/addons/l10n_es_intrastat_report/i18n/l10n_es_intrastat_report.pot
odoo/addons/l10n_es_intrastat_report/models/__init__.py
odoo/addons/l10n_es_intrastat_report/models/l10n_es_intrastat_product_declaration.py
odoo/addons/l10n_es_intrastat_report/models/stock_location.py
odoo/addons/l10n_es_intrastat_report/readme/CONFIGURE.rst
odoo/addons/l10n_es_intrastat_report/readme/CONTRIBUTORS.rst
odoo/addons/l10n_es_intrastat_report/readme/DESCRIPTION.rst
odoo/addons/l10n_es_intrastat_report/readme/INSTALL.rst
odoo/addons/l10n_es_intrastat_report/readme/ROADMAP.rst
odoo/addons/l10n_es_intrastat_report/readme/USAGE.rst
odoo/addons/l10n_es_intrastat_report/report/__init__.py
odoo/addons/l10n_es_intrastat_report/report/intrastat_product_report_xls.py
odoo/addons/l10n_es_intrastat_report/security/ir.model.access.csv
odoo/addons/l10n_es_intrastat_report/security/l10n_es_intrastat_report_security.xml
odoo/addons/l10n_es_intrastat_report/static/description/icon.png
odoo/addons/l10n_es_intrastat_report/static/description/index.html
odoo/addons/l10n_es_intrastat_report/views/l10n_es_intrastat_product.xml
odoo/addons/l10n_es_intrastat_report/wizards/__init__.py
odoo/addons/l10n_es_intrastat_report/wizards/l10n_es_intrastat_code_import.py
odoo/addons/l10n_es_intrastat_report/wizards/l10n_es_intrastat_code_import.xml
odoo11_addon_l10n_es_intrastat_report-11.0.1.0.3.dist-info/METADATA
odoo11_addon_l10n_es_intrastat_report-11.0.1.0.3.dist-info/WHEEL
odoo11_addon_l10n_es_intrastat_report-11.0.1.0.3.dist-info/top_level.txt
odoo11_addon_l10n_es_intrastat_report-11.0.1.0.3.dist-info/RECORD
